dbt/__init__.py
dbt/adapters/__init__.py
dbt/adapters/oracle/__init__.py
dbt/adapters/oracle/__version__.py
dbt/adapters/oracle/column.py
dbt/adapters/oracle/connection_helper.py
dbt/adapters/oracle/connections.py
dbt/adapters/oracle/impl.py
dbt/adapters/oracle/keyword_catalog.py
dbt/adapters/oracle/python_submissions.py
dbt/adapters/oracle/relation.py
dbt/adapters/oracle/relation_configs/__init__.py
dbt/adapters/oracle/relation_configs/base.py
dbt/adapters/oracle/relation_configs/materialized_view.py
dbt/adapters/oracle/relation_configs/policies.py
dbt/include/__init__.py
dbt/include/oracle/__init__.py
dbt/include/oracle/dbt_project.yml
dbt/include/oracle/profile_template.yml
dbt/include/oracle/macros/adapters.sql
dbt/include/oracle/macros/apply_grants.sql
dbt/include/oracle/macros/catalog.sql
dbt/include/oracle/macros/columns.sql
dbt/include/oracle/macros/freshness.sql
dbt/include/oracle/macros/schema_tests.sql
dbt/include/oracle/macros/show.sql
dbt/include/oracle/macros/update_legacy_snapshots.sql
dbt/include/oracle/macros/materializations/incremental/incremental.sql
dbt/include/oracle/macros/materializations/incremental/strategies.sql
dbt/include/oracle/macros/materializations/materialized_view/materialized_view.sql
dbt/include/oracle/macros/materializations/python_model/python.sql
dbt/include/oracle/macros/materializations/seed/seed.sql
dbt/include/oracle/macros/materializations/snapshot/snapshot.sql
dbt/include/oracle/macros/materializations/snapshot/snapshot_merge.sql
dbt/include/oracle/macros/materializations/snapshot/strategies.sql
dbt/include/oracle/macros/materializations/table/table.sql
dbt/include/oracle/macros/materializations/tests/helpers.sql
dbt/include/oracle/macros/materializations/view/view.sql
dbt/include/oracle/macros/relations/drop.sql
dbt/include/oracle/macros/utils/cast_bool_to_text.sql
dbt/include/oracle/macros/utils/data_types.sql
dbt/include/oracle/macros/utils/date_spine.sql
dbt/include/oracle/macros/utils/dateadd.sql
dbt_oracle-1.10.0.dist-info/licenses/LICENSE.txt
dbt_oracle-1.10.0.dist-info/METADATA
dbt_oracle-1.10.0.dist-info/WHEEL
dbt_oracle-1.10.0.dist-info/top_level.txt
dbt_oracle-1.10.0.dist-info/RECORD
